populate_synapse_nb/__init__.py
populate_synapse_nb/test_notebook.py
populate_synapse_nb-1.48.dist-info/LICENSE
populate_synapse_nb-1.48.dist-info/METADATA
populate_synapse_nb-1.48.dist-info/WHEEL
populate_synapse_nb-1.48.dist-info/top_level.txt
populate_synapse_nb-1.48.dist-info/RECORD
